lab_orchestrator_ws_proxy_lib/__init__.py
lab_orchestrator_ws_proxy_lib/ws_proxy_lib.py
lab_orchestrator_ws_proxy_lib-1.0.0.dist-info/LICENSE
lab_orchestrator_ws_proxy_lib-1.0.0.dist-info/METADATA
lab_orchestrator_ws_proxy_lib-1.0.0.dist-info/WHEEL
lab_orchestrator_ws_proxy_lib-1.0.0.dist-info/top_level.txt
lab_orchestrator_ws_proxy_lib-1.0.0.dist-info/zip-safe
lab_orchestrator_ws_proxy_lib-1.0.0.dist-info/RECORD
